objverify/__init__.py
objverify-1.0.1.dist-info/LICENSE
objverify-1.0.1.dist-info/WHEEL
objverify-1.0.1.dist-info/METADATA
objverify-1.0.1.dist-info/RECORD
