Metadata-Version: 2.1
Name: objverify
Version: 1.0.1
Summary: Super useful library for Python object validation
Keywords: object,validation,complex,schema,typechecking
Author-email: Carl Furtado <carlzfurtado@gmail.com>
Classifier: License :: OSI Approved :: MIT License
Classifier: Programming Language :: Python
Classifier: Programming Language :: Python :: 3
Classifier: Operating System :: OS Independent
Classifier: Intended Audience :: Developers
Classifier: Typing :: Typed
Project-URL: Home, https://github.com/User0332/objverify
